bygonessl/__init__.py
bygonessl/bygonessl.py
bygonessl-0.0.4.dist-info/METADATA
bygonessl-0.0.4.dist-info/RECORD
bygonessl-0.0.4.dist-info/WHEEL
bygonessl-0.0.4.dist-info/entry_points.txt
bygonessl-0.0.4.dist-info/top_level.txt
