Metadata-Version: 2.1
Name: bygonessl
Version: 0.0.4
Summary: A tool to discover bygonessl vulnerabilities
Home-page: https://github.com/dxa4481/bygonessl
Author: Dylan Ayrey
Author-email: dxa4481@rit.edu
License: GNU
Platform: UNKNOWN
Requires-Dist: pytz (==2018.5)
Requires-Dist: python-dateutil (==2.7.3)
Requires-Dist: requests (==2.19.1)
